[
  {
    "id": 1969278,
    "date": "2022-05-15T18:41:38",
    "date_gmt": "2022-05-15T21:41:38",
    "guid": {
      "rendered": "https://ricmais.com.br/?p=1969278"
    },
    "modified": "2022-05-15T18:42:41",
    "modified_gmt": "2022-05-15T21:42:41",
    "slug": "com-derrota-para-o-aruko-toledo-perde-chance-de-voltar-a-elite-do-paranaense",
    "status": "publish",
    "type": "post",
    "link": "https://ricmais.com.br/futebol/com-derrota-para-o-aruko-toledo-perde-chance-de-voltar-a-elite-do-paranaense/",
    "title": {
      "rendered": "Com derrota para o Aruko, Toledo perde chance de voltar à elite do Paranaense"
    },
    "content": {
      "rendered": "\n<p>Não será neste ano que o torcedor do Toledo reviverá seus momentos de glória. De Campeão da Taça Barcímio Sicupira Júnior em 2019 a quase rebaixado para a terceira divisão em 2022. Foi esse o cenário que, quem ainda se denomina torcedor, teve que enfrentar nesta temporada. O time foi de, cotado para ser campeão, para &#8220;ufa não caímos&#8221;, agora. </p>\n\n\n\n<p>A derrota por 1 a 0 para o Aruko só não rebaixou a equipe do Oeste porque o Verê empatou com o Iguaçu e o Apucarana acabou perdendo para o Andraus Brasil por 1 a 0. Com os resultados, quem caiu para a terceira divisão foi mesmo o Verê e a equipe do Prudentópolis. </p>\n\n\n\n<p>No próximo ano o Esporte Clube Toledo, equipe que será oficialmente lançada na próxima terça-feira (17), deve iniciar sua caminhada na terceira divisão do Paranaense. Por pouco, não teremos esse duelo entre dois clubes de uma cidade como Toledo, disputando a uma das vaga para a Segundona. Afinal, pra quem iria sua torcida?</p>\n\n\n\n<h2>Vinicius, o nome do jogo</h2>\n\n\n\n<p>O goleiro do Toledo foi o cara da partida. Primeiro que, se não fosse ele, o jogo terminaria com uma vantagem ainda maior, quem sabe até um chocolate. O que o moleque pegou foi brincadeira! A partida estava empatada, sem gols, sem graça e com chances mesmo só pro time visitante. </p>\n\n\n\n<ul><li><strong>Veja também: </strong><a href=\"https://ricmais.com.br/futebol/com-tcheco-no-comando-cascavel-tem-melhor-inicio-de-serie-d-da-historia-do-clube/\">Com Tcheco no comando, Cascavel tem melhor início de Série D da história do clube</a></li><li><a href=\"https://ricmais.com.br/futebol/grupo-ric-e-toledo-esporte-clube-realizam-sonho-das-campeas-dos-jeps/\">Grupo RIC e Toledo Esporte Clube realizam sonho das campeãs dos JEPS</a></li></ul>\n\n\n\n<p>Quando o Aruko chegava com perigo, Vinicius salvava como podia. Foram, no mínimo, quatro grandes chances de gols que o camisa 1 do Toledo salvou. Tudo parecia se encaminhar para aquele empate com gostinho de vitória, mas aos 44 da etapa final, a zaga bateu cabeça e o atacante André Carlos apareceu cara a cara com Vinicius, ai não teve chance. Golaço, por cobertura! Final de jogo, Aruko 1, Toledo 0. </p>\n\n\n\n<h3>Diversão de verdade</h3>\n\n\n\n<p>Quem pagou ingresso se divertiu mesmo vendo o doguinho correndo com a bola do jogo, fala aí, valeu a pena né?</p>\n\n\n\n<div class=\"wp-block-image\"><figure class=\"aligncenter size-large\"><img width=\"913\" height=\"600\" src=\"https://static.ricmais.com.br/uploads/2022/05/whatsapp-image-2022-05-15-at-17-24-19-913x600.jpeg\" alt=\"\" class=\"wp-image-1969285\" srcset=\"https://static.ricmais.com.br/uploads/2022/05/whatsapp-image-2022-05-15-at-17-24-19-913x600.jpeg 913w, https://static.ricmais.com.br/uploads/2022/05/whatsapp-image-2022-05-15-at-17-24-19-480x315.jpeg 480w, https://static.ricmais.com.br/uploads/2022/05/whatsapp-image-2022-05-15-at-17-24-19-768x505.jpeg 768w, https://static.ricmais.com.br/uploads/2022/05/whatsapp-image-2022-05-15-at-17-24-19.jpeg 1024w\" sizes=\"(max-width: 913px) 100vw, 913px\" /><figcaption>(Foto: Carlos / Movimento e Foco)</figcaption></figure></div>\n\n\n\n<h3>Como fica?</h3>\n\n\n\n<p>Agora quatro times vão em busca de duas vagas para a elite do Estadual. Aruko, Andraus, Foz do Iguaçu e PSTC ficaram com as quatro primeiras posições e se enfrentam na semifinal. O primeiro, encara o quarto e o segundo pega o terceiro colocado. </p>\n\n\n\n<p></p>\n",
      "protected": false
    },
    "excerpt": {
      "rendered": "<p>Não será neste ano que o torcedor do Toledo reviverá seus momentos de glória. De Campeão da Taça Barcímio Sicupira Júnior em 2019 a quase rebaixado para a terceira divisão em 2022. Foi esse o cenário que, quem ainda se denomina torcedor, teve que enfrentar nesta temporada. O time foi de, cotado para ser campeão, [&hellip;]</p>\n",
      "protected": false
    },
    "author": 262,
    "featured_media": 1969284,
    "comment_status": "closed",
    "ping_status": "closed",
    "sticky": false,
    "template": "",
    "format": "standard",
    "meta": [],
    "categories": [
      864
    ],
    "tags": [
      51110,
      51283,
      51049,
      53787,
      51210
    ],
    "_links": {
      "self": [
        {
          "href": "https://ricmais.com.br/wp-json/wp/v2/posts/1969278"
        }
      ],
      "collection": [
        {
          "href": "https://ricmais.com.br/wp-json/wp/v2/posts"
        }
      ],
      "about": [
        {
          "href": "https://ricmais.com.br/wp-json/wp/v2/types/post"
        }
      ],
      "author": [
        {
          "embeddable": true,
          "href": "https://ricmais.com.br/wp-json/wp/v2/users/262"
        }
      ],
      "replies": [
        {
          "embeddable": true,
          "href": "https://ricmais.com.br/wp-json/wp/v2/comments?post=1969278"
        }
      ],
      "version-history": [
        {
          "count": 0,
          "href": "https://ricmais.com.br/wp-json/wp/v2/posts/1969278/revisions"
        }
      ],
      "wp:featuredmedia": [
        {
          "embeddable": true,
          "href": "https://ricmais.com.br/wp-json/wp/v2/media/1969284"
        }
      ],
      "wp:attachment": [
        {
          "href": "https://ricmais.com.br/wp-json/wp/v2/media?parent=1969278"
        }
      ],
      "wp:term": [
        {
          "taxonomy": "category",
          "embeddable": true,
          "href": "https://ricmais.com.br/wp-json/wp/v2/categories?post=1969278"
        },
        {
          "taxonomy": "post_tag",
          "embeddable": true,
          "href": "https://ricmais.com.br/wp-json/wp/v2/tags?post=1969278"
        }
      ],
      "curies": [
        {
          "name": "wp",
          "href": "https://api.w.org/{rel}",
          "templated": true
        }
      ]
    },
    "_embedded": {
      "author": [
        {
          "id": 262,
          "name": "Maicon Wellington",
          "url": "",
          "description": "",
          "link": "https://ricmais.com.br/autor/maicon/",
          "slug": "maicon",
          "avatar_urls": {
            "24": "https://secure.gravatar.com/avatar/dfa818f3f7f77e5cd9c9fd5af79ee8e5?s=24&d=mm&r=g",
            "48": "https://secure.gravatar.com/avatar/dfa818f3f7f77e5cd9c9fd5af79ee8e5?s=48&d=mm&r=g",
            "96": "https://secure.gravatar.com/avatar/dfa818f3f7f77e5cd9c9fd5af79ee8e5?s=96&d=mm&r=g"
          },
          "_links": {
            "self": [
              {
                "href": "https://ricmais.com.br/wp-json/wp/v2/users/262"
              }
            ],
            "collection": [
              {
                "href": "https://ricmais.com.br/wp-json/wp/v2/users"
              }
            ]
          }
        }
      ],
      "wp:featuredmedia": [
        {
          "id": 1969284,
          "date": "2022-05-15T18:32:37",
          "slug": "toledo-perde-quase-rebaixado",
          "type": "attachment",
          "link": "https://ricmais.com.br/futebol/com-derrota-para-o-aruko-toledo-perde-chance-de-voltar-a-elite-do-paranaense/attachment/toledo-perde-quase-rebaixado/",
          "title": {
            "rendered": "toledo-perde-quase-rebaixado"
          },
          "author": 262,
          "caption": {
            "rendered": ""
          },
          "alt_text": "",
          "media_type": "image",
          "mime_type": "image/png",
          "media_details": {
            "width": 1920,
            "height": 1080,
            "file": "2022/05/toledo-perde-quase-rebaixado.png",
            "sizes": {
              "medium": {
                "file": "toledo-perde-quase-rebaixado-480x270.png",
                "width": 480,
                "height": 270,
                "mime_type": "image/png",
                "source_url": "https://static.ricmais.com.br/uploads/2022/05/toledo-perde-quase-rebaixado-480x270.png"
              },
              "large": {
                "file": "toledo-perde-quase-rebaixado-1067x600.png",
                "width": 1067,
                "height": 600,
                "mime_type": "image/png",
                "source_url": "https://static.ricmais.com.br/uploads/2022/05/toledo-perde-quase-rebaixado-1067x600.png"
              },
              "thumbnail": {
                "file": "toledo-perde-quase-rebaixado-150x150.png",
                "width": 150,
                "height": 150,
                "mime_type": "image/png",
                "source_url": "https://static.ricmais.com.br/uploads/2022/05/toledo-perde-quase-rebaixado-150x150.png"
              },
              "medium_large": {
                "file": "toledo-perde-quase-rebaixado-768x432.png",
                "width": 768,
                "height": 432,
                "mime_type": "image/png",
                "source_url": "https://static.ricmais.com.br/uploads/2022/05/toledo-perde-quase-rebaixado-768x432.png"
              },
              "1536x1536": {
                "file": "toledo-perde-quase-rebaixado-1536x864.png",
                "width": 1536,
                "height": 864,
                "mime_type": "image/png",
                "source_url": "https://static.ricmais.com.br/uploads/2022/05/toledo-perde-quase-rebaixado-1536x864.png"
              },
              "thumb_capa_small": {
                "file": "toledo-perde-quase-rebaixado-375x250.png",
                "width": 375,
                "height": 250,
                "mime_type": "image/png",
                "source_url": "https://static.ricmais.com.br/uploads/2022/05/toledo-perde-quase-rebaixado-375x250.png"
              },
              "thumb_4_colunas": {
                "file": "toledo-perde-quase-rebaixado-255x142.png",
                "width": 255,
                "height": 142,
                "mime_type": "image/png",
                "source_url": "https://static.ricmais.com.br/uploads/2022/05/toledo-perde-quase-rebaixado-255x142.png"
              },
              "thumb_3_colunas": {
                "file": "toledo-perde-quase-rebaixado-348x142.png",
                "width": 348,
                "height": 142,
                "mime_type": "image/png",
                "source_url": "https://static.ricmais.com.br/uploads/2022/05/toledo-perde-quase-rebaixado-348x142.png"
              },
              "thumb_programa": {
                "file": "toledo-perde-quase-rebaixado-348x164.png",
                "width": 348,
                "height": 164,
                "mime_type": "image/png",
                "source_url": "https://static.ricmais.com.br/uploads/2022/05/toledo-perde-quase-rebaixado-348x164.png"
              },
              "full": {
                "file": "toledo-perde-quase-rebaixado.png",
                "width": 1920,
                "height": 1080,
                "mime_type": "image/png",
                "source_url": "https://static.ricmais.com.br/uploads/2022/05/toledo-perde-quase-rebaixado.png"
              }
            },
            "image_meta": {
              "aperture": "0",
              "credit": "",
              "camera": "",
              "caption": "",
              "created_timestamp": "0",
              "copyright": "",
              "focal_length": "0",
              "iso": "0",
              "shutter_speed": "0",
              "title": "",
              "orientation": "0",
              "keywords": []
            }
          },
          "source_url": "https://static.ricmais.com.br/uploads/2022/05/toledo-perde-quase-rebaixado.png",
          "_links": {
            "self": [
              {
                "href": "https://ricmais.com.br/wp-json/wp/v2/media/1969284"
              }
            ],
            "collection": [
              {
                "href": "https://ricmais.com.br/wp-json/wp/v2/media"
              }
            ],
            "about": [
              {
                "href": "https://ricmais.com.br/wp-json/wp/v2/types/attachment"
              }
            ],
            "author": [
              {
                "embeddable": true,
                "href": "https://ricmais.com.br/wp-json/wp/v2/users/262"
              }
            ],
            "replies": [
              {
                "embeddable": true,
                "href": "https://ricmais.com.br/wp-json/wp/v2/comments?post=1969284"
              }
            ]
          }
        }
      ],
      "wp:term": [
        [
          {
            "id": 864,
            "link": "https://ricmais.com.br/futebol/",
            "name": "Futebol",
            "slug": "futebol",
            "taxonomy": "category",
            "_links": {
              "self": [
                {
                  "href": "https://ricmais.com.br/wp-json/wp/v2/categories/864"
                }
              ],
              "collection": [
                {
                  "href": "https://ricmais.com.br/wp-json/wp/v2/categories"
                }
              ],
              "about": [
                {
                  "href": "https://ricmais.com.br/wp-json/wp/v2/taxonomies/category"
                }
              ],
              "wp:post_type": [
                {
                  "href": "https://ricmais.com.br/wp-json/wp/v2/posts?categories=864"
                }
              ],
              "curies": [
                {
                  "name": "wp",
                  "href": "https://api.w.org/{rel}",
                  "templated": true
                }
              ]
            }
          }
        ],
        [
          {
            "id": 51283,
            "link": "https://ricmais.com.br/tag/cascavel/",
            "name": "Cascavel",
            "slug": "cascavel",
            "taxonomy": "post_tag",
            "_links": {
              "self": [
                {
                  "href": "https://ricmais.com.br/wp-json/wp/v2/tags/51283"
                }
              ],
              "collection": [
                {
                  "href": "https://ricmais.com.br/wp-json/wp/v2/tags"
                }
              ],
              "about": [
                {
                  "href": "https://ricmais.com.br/wp-json/wp/v2/taxonomies/post_tag"
                }
              ],
              "wp:post_type": [
                {
                  "href": "https://ricmais.com.br/wp-json/wp/v2/posts?tags=51283"
                }
              ],
              "curies": [
                {
                  "name": "wp",
                  "href": "https://api.w.org/{rel}",
                  "templated": true
                }
              ]
            }
          },
          {
            "id": 51049,
            "link": "https://ricmais.com.br/tag/esportes/",
            "name": "Esportes",
            "slug": "esportes",
            "taxonomy": "post_tag",
            "_links": {
              "self": [
                {
                  "href": "https://ricmais.com.br/wp-json/wp/v2/tags/51049"
                }
              ],
              "collection": [
                {
                  "href": "https://ricmais.com.br/wp-json/wp/v2/tags"
                }
              ],
              "about": [
                {
                  "href": "https://ricmais.com.br/wp-json/wp/v2/taxonomies/post_tag"
                }
              ],
              "wp:post_type": [
                {
                  "href": "https://ricmais.com.br/wp-json/wp/v2/posts?tags=51049"
                }
              ],
              "curies": [
                {
                  "name": "wp",
                  "href": "https://api.w.org/{rel}",
                  "templated": true
                }
              ]
            }
          },
          {
            "id": 53787,
            "link": "https://ricmais.com.br/tag/maicon-wellington/",
            "name": "Maicon Wellington",
            "slug": "maicon-wellington",
            "taxonomy": "post_tag",
            "_links": {
              "self": [
                {
                  "href": "https://ricmais.com.br/wp-json/wp/v2/tags/53787"
                }
              ],
              "collection": [
                {
                  "href": "https://ricmais.com.br/wp-json/wp/v2/tags"
                }
              ],
              "about": [
                {
                  "href": "https://ricmais.com.br/wp-json/wp/v2/taxonomies/post_tag"
                }
              ],
              "wp:post_type": [
                {
                  "href": "https://ricmais.com.br/wp-json/wp/v2/posts?tags=53787"
                }
              ],
              "curies": [
                {
                  "name": "wp",
                  "href": "https://api.w.org/{rel}",
                  "templated": true
                }
              ]
            }
          },
          {
            "id": 51210,
            "link": "https://ricmais.com.br/tag/post-de-blog/",
            "name": "Post de blog",
            "slug": "post-de-blog",
            "taxonomy": "post_tag",
            "_links": {
              "self": [
                {
                  "href": "https://ricmais.com.br/wp-json/wp/v2/tags/51210"
                }
              ],
              "collection": [
                {
                  "href": "https://ricmais.com.br/wp-json/wp/v2/tags"
                }
              ],
              "about": [
                {
                  "href": "https://ricmais.com.br/wp-json/wp/v2/taxonomies/post_tag"
                }
              ],
              "wp:post_type": [
                {
                  "href": "https://ricmais.com.br/wp-json/wp/v2/posts?tags=51210"
                }
              ],
              "curies": [
                {
                  "name": "wp",
                  "href": "https://api.w.org/{rel}",
                  "templated": true
                }
              ]
            }
          }
        ]
      ]
    }
  },
  {
    "id": 1969276,
    "date": "2022-05-15T17:49:05",
    "date_gmt": "2022-05-15T20:49:05",
    "guid": {
      "rendered": "https://ricmais.com.br/?p=1969276"
    },
    "modified": "2022-05-15T17:49:10",
    "modified_gmt": "2022-05-15T20:49:10",
    "slug": "motorista-morre-apos-batida-de-frente-entre-dois-carros-na-pr-364",
    "status": "publish",
    "type": "post",
    "link": "https://ricmais.com.br/seguranca/acidentes/motorista-morre-apos-batida-de-frente-entre-dois-carros-na-pr-364/",
    "title": {
      "rendered": "Motorista morre após batida de frente entre dois carros na PR-364"
    },
    "content": {
      "rendered": "\n<p>Um motorista de 37 anos morreu depois de uma batida de frente entre dois carros, na tarde de sábado (14), na PR-364, em Palotina no oeste do Paraná. </p>\n\n\n\n<p>De acordo com a Polícia Rodoviária Estadual (PRE), o motorista, de 45 anos, e uma criança, de 7 anos, que estavam no outro carro, sofreram ferimentos leves e foram socorridos.</p>\n\n\n\n<p>A polícia informou que o veículo onde estava a vítima fatal foi atingido pelo outro carro. A pista estava molhada no momento do acidente.</p>\n",
      "protected": false
    },
    "excerpt": {
      "rendered": "<p>Um motorista de 37 anos morreu depois de uma batida de frente entre dois carros, na tarde de sábado (14), na PR-364, em Palotina no oeste do Paraná. De acordo com a Polícia Rodoviária Estadual (PRE), o motorista, de 45 anos, e uma criança, de 7 anos, que estavam no outro carro, sofreram ferimentos leves [&hellip;]</p>\n",
      "protected": false
    },
    "author": 233,
    "featured_media": 1969277,
    "comment_status": "closed",
    "ping_status": "closed",
    "sticky": false,
    "template": "",
    "format": "standard",
    "meta": [],
    "categories": [
      53685
    ],
    "tags": [
      51208,
      51465
    ],
    "_links": {
      "self": [
        {
          "href": "https://ricmais.com.br/wp-json/wp/v2/posts/1969276"
        }
      ],
      "collection": [
        {
          "href": "https://ricmais.com.br/wp-json/wp/v2/posts"
        }
      ],
      "about": [
        {
          "href": "https://ricmais.com.br/wp-json/wp/v2/types/post"
        }
      ],
      "author": [
        {
          "embeddable": true,
          "href": "https://ricmais.com.br/wp-json/wp/v2/users/233"
        }
      ],
      "replies": [
        {
          "embeddable": true,
          "href": "https://ricmais.com.br/wp-json/wp/v2/comments?post=1969276"
        }
      ],
      "version-history": [
        {
          "count": 0,
          "href": "https://ricmais.com.br/wp-json/wp/v2/posts/1969276/revisions"
        }
      ],
      "wp:featuredmedia": [
        {
          "embeddable": true,
          "href": "https://ricmais.com.br/wp-json/wp/v2/media/1969277"
        }
      ],
      "wp:attachment": [
        {
          "href": "https://ricmais.com.br/wp-json/wp/v2/media?parent=1969276"
        }
      ],
      "wp:term": [
        {
          "taxonomy": "category",
          "embeddable": true,
          "href": "https://ricmais.com.br/wp-json/wp/v2/categories?post=1969276"
        },
        {
          "taxonomy": "post_tag",
          "embeddable": true,
          "href": "https://ricmais.com.br/wp-json/wp/v2/tags?post=1969276"
        }
      ],
      "curies": [
        {
          "name": "wp",
          "href": "https://api.w.org/{rel}",
          "templated": true
        }
      ]
    },
    "_embedded": {
      "author": [
        {
          "id": 233,
          "name": "Redação RIC Mais",
          "url": "",
          "description": "",
          "link": "https://ricmais.com.br/autor/redacao/",
          "slug": "redacao",
          "avatar_urls": {
            "24": "https://secure.gravatar.com/avatar/2dc10d0b11d1c7ef917118536b9ffa58?s=24&d=mm&r=g",
            "48": "https://secure.gravatar.com/avatar/2dc10d0b11d1c7ef917118536b9ffa58?s=48&d=mm&r=g",
            "96": "https://secure.gravatar.com/avatar/2dc10d0b11d1c7ef917118536b9ffa58?s=96&d=mm&r=g"
          },
          "_links": {
            "self": [
              {
                "href": "https://ricmais.com.br/wp-json/wp/v2/users/233"
              }
            ],
            "collection": [
              {
                "href": "https://ricmais.com.br/wp-json/wp/v2/users"
              }
            ]
          }
        }
      ],
      "wp:featuredmedia": [
        {
          "id": 1969277,
          "date": "2022-05-15T17:48:21",
          "slug": "acidente_cruzeok",
          "type": "attachment",
          "link": "https://ricmais.com.br/seguranca/acidentes/motorista-morre-apos-batida-de-frente-entre-dois-carros-na-pr-364/attachment/acidente_cruzeok/",
          "title": {
            "rendered": "acidente_cruzeOK"
          },
          "author": 2190,
          "caption": {
            "rendered": "<p>Motorista morre após batida de frente entre dois carros na PR-364 (Foto: PRE/Divulgação)</p>\n"
          },
          "alt_text": "",
          "media_type": "image",
          "mime_type": "image/jpeg",
          "media_details": {
            "width": 768,
            "height": 1024,
            "file": "2022/05/acidente_cruzeok.jpg",
            "sizes": {
              "medium": {
                "file": "acidente_cruzeok-360x480.jpg",
                "width": 360,
                "height": 480,
                "mime_type": "image/jpeg",
                "source_url": "https://static.ricmais.com.br/uploads/2022/05/acidente_cruzeok-360x480.jpg"
              },
              "large": {
                "file": "acidente_cruzeok-450x600.jpg",
                "width": 450,
                "height": 600,
                "mime_type": "image/jpeg",
                "source_url": "https://static.ricmais.com.br/uploads/2022/05/acidente_cruzeok-450x600.jpg"
              },
              "thumbnail": {
                "file": "acidente_cruzeok-150x150.jpg",
                "width": 150,
                "height": 150,
                "mime_type": "image/jpeg",
                "source_url": "https://static.ricmais.com.br/uploads/2022/05/acidente_cruzeok-150x150.jpg"
              },
              "thumb_capa_small": {
                "file": "acidente_cruzeok-375x250.jpg",
                "width": 375,
                "height": 250,
                "mime_type": "image/jpeg",
                "source_url": "https://static.ricmais.com.br/uploads/2022/05/acidente_cruzeok-375x250.jpg"
              },
              "thumb_4_colunas": {
                "file": "acidente_cruzeok-255x142.jpg",
                "width": 255,
                "height": 142,
                "mime_type": "image/jpeg",
                "source_url": "https://static.ricmais.com.br/uploads/2022/05/acidente_cruzeok-255x142.jpg"
              },
              "thumb_3_colunas": {
                "file": "acidente_cruzeok-348x142.jpg",
                "width": 348,
                "height": 142,
                "mime_type": "image/jpeg",
                "source_url": "https://static.ricmais.com.br/uploads/2022/05/acidente_cruzeok-348x142.jpg"
              },
              "thumb_programa": {
                "file": "acidente_cruzeok-348x164.jpg",
                "width": 348,
                "height": 164,
                "mime_type": "image/jpeg",
                "source_url": "https://static.ricmais.com.br/uploads/2022/05/acidente_cruzeok-348x164.jpg"
              },
              "full": {
                "file": "acidente_cruzeok.jpg",
                "width": 768,
                "height": 1024,
                "mime_type": "image/jpeg",
                "source_url": "https://static.ricmais.com.br/uploads/2022/05/acidente_cruzeok.jpg"
              }
            },
            "image_meta": {
              "aperture": "0",
              "credit": "",
              "camera": "",
              "caption": "",
              "created_timestamp": "0",
              "copyright": "",
              "focal_length": "0",
              "iso": "0",
              "shutter_speed": "0",
              "title": "",
              "orientation": "1",
              "keywords": []
            }
          },
          "source_url": "https://static.ricmais.com.br/uploads/2022/05/acidente_cruzeok.jpg",
          "_links": {
            "self": [
              {
                "href": "https://ricmais.com.br/wp-json/wp/v2/media/1969277"
              }
            ],
            "collection": [
              {
                "href": "https://ricmais.com.br/wp-json/wp/v2/media"
              }
            ],
            "about": [
              {
                "href": "https://ricmais.com.br/wp-json/wp/v2/types/attachment"
              }
            ],
            "author": [
              {
                "embeddable": true,
                "href": "https://ricmais.com.br/wp-json/wp/v2/users/2190"
              }
            ],
            "replies": [
              {
                "embeddable": true,
                "href": "https://ricmais.com.br/wp-json/wp/v2/comments?post=1969277"
              }
            ]
          }
        }
      ],
      "wp:term": [
        [
          {
            "id": 53685,
            "link": "https://ricmais.com.br/seguranca/acidentes/",
            "name": "Acidentes",
            "slug": "acidentes",
            "taxonomy": "category",
            "_links": {
              "self": [
                {
                  "href": "https://ricmais.com.br/wp-json/wp/v2/categories/53685"
                }
              ],
              "collection": [
                {
                  "href": "https://ricmais.com.br/wp-json/wp/v2/categories"
                }
              ],
              "about": [
                {
                  "href": "https://ricmais.com.br/wp-json/wp/v2/taxonomies/category"
                }
              ],
              "up": [
                {
                  "embeddable": true,
                  "href": "https://ricmais.com.br/wp-json/wp/v2/categories/862"
                }
              ],
              "wp:post_type": [
                {
                  "href": "https://ricmais.com.br/wp-json/wp/v2/posts?categories=53685"
                }
              ],
              "curies": [
                {
                  "name": "wp",
                  "href": "https://api.w.org/{rel}",
                  "templated": true
                }
              ]
            }
          }
        ],
        [
          {
            "id": 51208,
            "link": "https://ricmais.com.br/tag/noticia/",
            "name": "Notícia",
            "slug": "noticia",
            "taxonomy": "post_tag",
            "_links": {
              "self": [
                {
                  "href": "https://ricmais.com.br/wp-json/wp/v2/tags/51208"
                }
              ],
              "collection": [
                {
                  "href": "https://ricmais.com.br/wp-json/wp/v2/tags"
                }
              ],
              "about": [
                {
                  "href": "https://ricmais.com.br/wp-json/wp/v2/taxonomies/post_tag"
                }
              ],
              "wp:post_type": [
                {
                  "href": "https://ricmais.com.br/wp-json/wp/v2/posts?tags=51208"
                }
              ],
              "curies": [
                {
                  "name": "wp",
                  "href": "https://api.w.org/{rel}",
                  "templated": true
                }
              ]
            }
          },
          {
            "id": 51465,
            "link": "https://ricmais.com.br/tag/palotina/",
            "name": "Palotina",
            "slug": "palotina",
            "taxonomy": "post_tag",
            "_links": {
              "self": [
                {
                  "href": "https://ricmais.com.br/wp-json/wp/v2/tags/51465"
                }
              ],
              "collection": [
                {
                  "href": "https://ricmais.com.br/wp-json/wp/v2/tags"
                }
              ],
              "about": [
                {
                  "href": "https://ricmais.com.br/wp-json/wp/v2/taxonomies/post_tag"
                }
              ],
              "wp:post_type": [
                {
                  "href": "https://ricmais.com.br/wp-json/wp/v2/posts?tags=51465"
                }
              ],
              "curies": [
                {
                  "name": "wp",
                  "href": "https://api.w.org/{rel}",
                  "templated": true
                }
              ]
            }
          }
        ]
      ]
    }
  },
  {
    "id": 1969269,
    "date": "2022-05-15T17:18:35",
    "date_gmt": "2022-05-15T20:18:35",
    "guid": {
      "rendered": "https://ricmais.com.br/?p=1969269"
    },
    "modified": "2022-05-15T17:19:46",
    "modified_gmt": "2022-05-15T20:19:46",
    "slug": "semana-comeca-com-temperaturas-em-queda-no-pr-termometros-podem-chegar-a-0oc",
    "status": "publish",
    "type": "post",
    "link": "https://ricmais.com.br/clima-tempo/semana-comeca-com-temperaturas-em-queda-no-pr-termometros-podem-chegar-a-0oc/",
    "title": {
      "rendered": "Semana começa com temperaturas em queda no PR; termômetros podem chegar a 0ºC"
    },
    "content": {
      "rendered": "\n<p>A partir desta segunda-feira (16), as temperaturas devem despencar no Paraná, com a chegada de uma onda de frio aos estados do Sul do país. Neste domingo (15), as temperaturas estão amenas, mas nos próximos dias ocorre forte resfriamento, conforme o Simepar.</p>\n\n\n\n<p>Na segunda, que tem previsão de pouca chuva no estado, ainda haverá presença de nuvens e nevoeiros ao amanhecer em algumas região. </p>\n\n\n\n<p>A partir da tarde, o sol deve predominar na maior parte do estado, com possibilidade de garoa apenas nas praias. À noite, deve esfriar rapidamente devido à presença de massa polar. </p>\n\n\n\n<ul><li><strong>Leia também:</strong> <a href=\"https://ricmais.com.br/clima-tempo/primeira-onda-de-frio-chega-ao-sul-do-brasil-veja-em-qual-regiao-pode-nevar/\">Primeira onda de frio chega ao Sul; veja em qual região pode nevar</a></li></ul>\n\n\n\n<p>De acordo com o Simepar, o frio mais intenso deve chegar ao estado entre terça-feira (17) e quinta-feira (19). Um ar polar vai predominar no estado. O céu continuará com muita nebulosidade, o que impede a formação de geadas mais generealizadas.</p>\n\n\n\n<p>Porém, o Simepar não descarta a possibilidade de chuva congelada em algumas regiões do Paraná. Há possibilidade de neve nas serras gaúcha e catarinense, principalmente na terça.</p>\n\n\n\n<p>Neste dia, as temperaturas mínimas nas cidades paranaenses não devem passar de 6ºC, exceto no litoral. Veja a imagem abaixo com a previsão para a terça.</p>\n\n\n\n<figure class=\"wp-block-image size-large\"><img width=\"1092\" height=\"454\" src=\"https://static.ricmais.com.br/uploads/2022/05/prev-terca-1092x454.png\" alt=\"\" class=\"wp-image-1969273\" srcset=\"https://static.ricmais.com.br/uploads/2022/05/prev-terca-1092x454.png 1092w, https://static.ricmais.com.br/uploads/2022/05/prev-terca-480x200.png 480w, https://static.ricmais.com.br/uploads/2022/05/prev-terca-768x320.png 768w, https://static.ricmais.com.br/uploads/2022/05/prev-terca-1536x639.png 1536w, https://static.ricmais.com.br/uploads/2022/05/prev-terca.png 1920w\" sizes=\"(max-width: 1092px) 100vw, 1092px\" /><figcaption>Na terça (17), as temperaturas mínimas nas cidades paranaenses não devem passar de 6ºC, exceto no litoral (Foto: Simepar)</figcaption></figure>\n\n\n\n<blockquote class=\"wp-block-quote\"><p>&#8220;A tendência é de termos temperaturas mais baixas no Paraná entre o sul, centro e leste. Teremos dias e noites bastante geladas em todo o estado. O vento deixa a sensação de frio ainda maior&#8221;,</p><cite>afirma o meteorologista Lizandro Jacóbsen.</cite></blockquote>\n\n\n\n<p>A massa de ar polar mantém as temperaturas bastante baixas no estado durante o restante da semana. Mas, com o céu mais aberto, o risco de geadas aumenta.</p>\n",
      "protected": false
    },
    "excerpt": {
      "rendered": "<p>A partir desta segunda-feira (16), as temperaturas devem despencar no Paraná, com a chegada de uma onda de frio aos estados do Sul do país. Neste domingo (15), as temperaturas estão amenas, mas nos próximos dias ocorre forte resfriamento, conforme o Simepar. Na segunda, que tem previsão de pouca chuva no estado, ainda haverá presença [&hellip;]</p>\n",
      "protected": false
    },
    "author": 233,
    "featured_media": 1953488,
    "comment_status": "closed",
    "ping_status": "closed",
    "sticky": false,
    "template": "",
    "format": "standard",
    "meta": [],
    "categories": [
      50929
    ],
    "tags": [
      51034,
      51208,
      51628
    ],
    "_links": {
      "self": [
        {
          "href": "https://ricmais.com.br/wp-json/wp/v2/posts/1969269"
        }
      ],
      "collection": [
        {
          "href": "https://ricmais.com.br/wp-json/wp/v2/posts"
        }
      ],
      "about": [
        {
          "href": "https://ricmais.com.br/wp-json/wp/v2/types/post"
        }
      ],
      "author": [
        {
          "embeddable": true,
          "href": "https://ricmais.com.br/wp-json/wp/v2/users/233"
        }
      ],
      "replies": [
        {
          "embeddable": true,
          "href": "https://ricmais.com.br/wp-json/wp/v2/comments?post=1969269"
        }
      ],
      "version-history": [
        {
          "count": 0,
          "href": "https://ricmais.com.br/wp-json/wp/v2/posts/1969269/revisions"
        }
      ],
      "wp:featuredmedia": [
        {
          "embeddable": true,
          "href": "https://ricmais.com.br/wp-json/wp/v2/media/1953488"
        }
      ],
      "wp:attachment": [
        {
          "href": "https://ricmais.com.br/wp-json/wp/v2/media?parent=1969269"
        }
      ],
      "wp:term": [
        {
          "taxonomy": "category",
          "embeddable": true,
          "href": "https://ricmais.com.br/wp-json/wp/v2/categories?post=1969269"
        },
        {
          "taxonomy": "post_tag",
          "embeddable": true,
          "href": "https://ricmais.com.br/wp-json/wp/v2/tags?post=1969269"
        }
      ],
      "curies": [
        {
          "name": "wp",
          "href": "https://api.w.org/{rel}",
          "templated": true
        }
      ]
    },
    "_embedded": {
      "author": [
        {
          "id": 233,
          "name": "Redação RIC Mais",
          "url": "",
          "description": "",
          "link": "https://ricmais.com.br/autor/redacao/",
          "slug": "redacao",
          "avatar_urls": {
            "24": "https://secure.gravatar.com/avatar/2dc10d0b11d1c7ef917118536b9ffa58?s=24&d=mm&r=g",
            "48": "https://secure.gravatar.com/avatar/2dc10d0b11d1c7ef917118536b9ffa58?s=48&d=mm&r=g",
            "96": "https://secure.gravatar.com/avatar/2dc10d0b11d1c7ef917118536b9ffa58?s=96&d=mm&r=g"
          },
          "_links": {
            "self": [
              {
                "href": "https://ricmais.com.br/wp-json/wp/v2/users/233"
              }
            ],
            "collection": [
              {
                "href": "https://ricmais.com.br/wp-json/wp/v2/users"
              }
            ]
          }
        }
      ],
      "wp:featuredmedia": [
        {
          "id": 1953488,
          "date": "2022-04-15T08:25:23",
          "slug": "frio-parana-2",
          "type": "attachment",
          "link": "https://ricmais.com.br/clima-tempo/general-carneiro-registra-menor-temperatura-do-ano-no-parana-com-08-oc-veja-as-minimas/attachment/frio-parana-2/",
          "title": {
            "rendered": "frio-parana"
          },
          "author": 1179,
          "caption": {
            "rendered": "<p>(Foto: Gilson Abreu/ AEN) </p>\n"
          },
          "alt_text": "",
          "media_type": "image",
          "mime_type": "image/png",
          "media_details": {
            "width": 3000,
            "height": 2000,
            "file": "2022/04/frio-parana.png",
            "sizes": {
              "medium": {
                "file": "frio-parana-480x320.png",
                "width": 480,
                "height": 320,
                "mime_type": "image/png",
                "source_url": "https://static.ricmais.com.br/uploads/2022/04/frio-parana-480x320.png"
              },
              "large": {
                "file": "frio-parana-900x600.png",
                "width": 900,
                "height": 600,
                "mime_type": "image/png",
                "source_url": "https://static.ricmais.com.br/uploads/2022/04/frio-parana-900x600.png"
              },
              "thumbnail": {
                "file": "frio-parana-150x150.png",
                "width": 150,
                "height": 150,
                "mime_type": "image/png",
                "source_url": "https://static.ricmais.com.br/uploads/2022/04/frio-parana-150x150.png"
              },
              "medium_large": {
                "file": "frio-parana-768x512.png",
                "width": 768,
                "height": 512,
                "mime_type": "image/png",
                "source_url": "https://static.ricmais.com.br/uploads/2022/04/frio-parana-768x512.png"
              },
              "1536x1536": {
                "file": "frio-parana-1536x1024.png",
                "width": 1536,
                "height": 1024,
                "mime_type": "image/png",
                "source_url": "https://static.ricmais.com.br/uploads/2022/04/frio-parana-1536x1024.png"
              },
              "2048x2048": {
                "file": "frio-parana-2048x1365.png",
                "width": 2048,
                "height": 1365,
                "mime_type": "image/png",
                "source_url": "https://static.ricmais.com.br/uploads/2022/04/frio-parana-2048x1365.png"
              },
              "thumb_capa_small": {
                "file": "frio-parana-375x250.png",
                "width": 375,
                "height": 250,
                "mime_type": "image/png",
                "source_url": "https://static.ricmais.com.br/uploads/2022/04/frio-parana-375x250.png"
              },
              "thumb_4_colunas": {
                "file": "frio-parana-255x142.png",
                "width": 255,
                "height": 142,
                "mime_type": "image/png",
                "source_url": "https://static.ricmais.com.br/uploads/2022/04/frio-parana-255x142.png"
              },
              "thumb_3_colunas": {
                "file": "frio-parana-348x142.png",
                "width": 348,
                "height": 142,
                "mime_type": "image/png",
                "source_url": "https://static.ricmais.com.br/uploads/2022/04/frio-parana-348x142.png"
              },
              "thumb_programa": {
                "file": "frio-parana-348x164.png",
                "width": 348,
                "height": 164,
                "mime_type": "image/png",
                "source_url": "https://static.ricmais.com.br/uploads/2022/04/frio-parana-348x164.png"
              },
              "full": {
                "file": "frio-parana.png",
                "width": 3000,
                "height": 2000,
                "mime_type": "image/png",
                "source_url": "https://static.ricmais.com.br/uploads/2022/04/frio-parana.png"
              }
            },
            "image_meta": {
              "aperture": "0",
              "credit": "",
              "camera": "",
              "caption": "",
              "created_timestamp": "0",
              "copyright": "",
              "focal_length": "0",
              "iso": "0",
              "shutter_speed": "0",
              "title": "",
              "orientation": "0",
              "keywords": []
            }
          },
          "source_url": "https://static.ricmais.com.br/uploads/2022/04/frio-parana.png",
          "_links": {
            "self": [
              {
                "href": "https://ricmais.com.br/wp-json/wp/v2/media/1953488"
              }
            ],
            "collection": [
              {
                "href": "https://ricmais.com.br/wp-json/wp/v2/media"
              }
            ],
            "about": [
              {
                "href": "https://ricmais.com.br/wp-json/wp/v2/types/attachment"
              }
            ],
            "author": [
              {
                "embeddable": true,
                "href": "https://ricmais.com.br/wp-json/wp/v2/users/1179"
              }
            ],
            "replies": [
              {
                "embeddable": true,
                "href": "https://ricmais.com.br/wp-json/wp/v2/comments?post=1953488"
              }
            ]
          }
        }
      ],
      "wp:term": [
        [
          {
            "id": 50929,
            "link": "https://ricmais.com.br/clima-tempo/",
            "name": "Clima e Tempo",
            "slug": "clima-tempo",
            "taxonomy": "category",
            "_links": {
              "self": [
                {
                  "href": "https://ricmais.com.br/wp-json/wp/v2/categories/50929"
                }
              ],
              "collection": [
                {
                  "href": "https://ricmais.com.br/wp-json/wp/v2/categories"
                }
              ],
              "about": [
                {
                  "href": "https://ricmais.com.br/wp-json/wp/v2/taxonomies/category"
                }
              ],
              "wp:post_type": [
                {
                  "href": "https://ricmais.com.br/wp-json/wp/v2/posts?categories=50929"
                }
              ],
              "curies": [
                {
                  "name": "wp",
                  "href": "https://api.w.org/{rel}",
                  "templated": true
                }
              ]
            }
          }
        ],
        [
          {
            "id": 51034,
            "link": "https://ricmais.com.br/tag/cotidiano/",
            "name": "Cotidiano",
            "slug": "cotidiano",
            "taxonomy": "post_tag",
            "_links": {
              "self": [
                {
                  "href": "https://ricmais.com.br/wp-json/wp/v2/tags/51034"
                }
              ],
              "collection": [
                {
                  "href": "https://ricmais.com.br/wp-json/wp/v2/tags"
                }
              ],
              "about": [
                {
                  "href": "https://ricmais.com.br/wp-json/wp/v2/taxonomies/post_tag"
                }
              ],
              "wp:post_type": [
                {
                  "href": "https://ricmais.com.br/wp-json/wp/v2/posts?tags=51034"
                }
              ],
              "curies": [
                {
                  "name": "wp",
                  "href": "https://api.w.org/{rel}",
                  "templated": true
                }
              ]
            }
          },
          {
            "id": 51208,
            "link": "https://ricmais.com.br/tag/noticia/",
            "name": "Notícia",
            "slug": "noticia",
            "taxonomy": "post_tag",
            "_links": {
              "self": [
                {
                  "href": "https://ricmais.com.br/wp-json/wp/v2/tags/51208"
                }
              ],
              "collection": [
                {
                  "href": "https://ricmais.com.br/wp-json/wp/v2/tags"
                }
              ],
              "about": [
                {
                  "href": "https://ricmais.com.br/wp-json/wp/v2/taxonomies/post_tag"
                }
              ],
              "wp:post_type": [
                {
                  "href": "https://ricmais.com.br/wp-json/wp/v2/posts?tags=51208"
                }
              ],
              "curies": [
                {
                  "name": "wp",
                  "href": "https://api.w.org/{rel}",
                  "templated": true
                }
              ]
            }
          },
          {
            "id": 51628,
            "link": "https://ricmais.com.br/tag/parana/",
            "name": "Paraná",
            "slug": "parana",
            "taxonomy": "post_tag",
            "_links": {
              "self": [
                {
                  "href": "https://ricmais.com.br/wp-json/wp/v2/tags/51628"
                }
              ],
              "collection": [
                {
                  "href": "https://ricmais.com.br/wp-json/wp/v2/tags"
                }
              ],
              "about": [
                {
                  "href": "https://ricmais.com.br/wp-json/wp/v2/taxonomies/post_tag"
                }
              ],
              "wp:post_type": [
                {
                  "href": "https://ricmais.com.br/wp-json/wp/v2/posts?tags=51628"
                }
              ],
              "curies": [
                {
                  "name": "wp",
                  "href": "https://api.w.org/{rel}",
                  "templated": true
                }
              ]
            }
          }
        ]
      ]
    }
  },
  {
    "id": 1969238,
    "date": "2022-05-15T17:03:14",
    "date_gmt": "2022-05-15T20:03:14",
    "guid": {
      "rendered": "https://ricmais.com.br/?p=1969238"
    },
    "modified": "2022-05-15T17:03:17",
    "modified_gmt": "2022-05-15T20:03:17",
    "slug": "parana-clube-vence-perolas-negras-por-1-a-0",
    "status": "publish",
    "type": "post",
    "link": "https://ricmais.com.br/futebol/parana-clube-vence-perolas-negras-por-1-a-0/",
    "title": {
      "rendered": "Paraná Clube vence o Pérolas Negras-RJ por 1 a 0 e se mantém na vice-liderança do Grupo 7 da Série D"
    },
    "content": {
      "rendered": "\n<p>Na tarde deste domingo (15),&nbsp;<strong>Pérolas Negras-RJ&nbsp;</strong>e&nbsp;<strong>Paraná Clube</strong>, se enfrentaram, no&nbsp;<strong>Estádio do Trabalhador</strong>, pela&nbsp;<strong>quinta rodada</strong>&nbsp;do Grupo 7 da&nbsp;<strong>Série D&nbsp;</strong>do Campeonato Brasileiro.</p>\n\n\n\n<p>O <strong>Tricolor </strong>sofreu mais que o necessário, mas <strong>conseguiu vencer </strong>a sua segunda partida na competição, e segue dando sequência ao bom momento no campeonato. <strong>André Krobel</strong> <strong>perdeu um pênalti</strong> na primeira etapa, mas a equipe <strong>paranista </strong>mostrou disposição e <strong>conseguiu garantir o triunfo </strong>no segundo tempo, com <strong>gol </strong>marcado por <strong>Éverton Britto</strong>.</p>\n\n\n\n<p>Com o resultado, que derruba um jejum de mais de dez meses sem vitórias fora de casa, o <strong>Paraná Clube</strong>, ainda invicto, chega aos <strong>nove pontos</strong>, e se mantém na <strong>vice-liderança</strong>, <strong>dois pontos atrás</strong> do <strong>São Bernardo-SP</strong>. Já o <strong>Pérolas Negras</strong>, que ainda não venceu, permanece com<strong> três pontos</strong>, em <strong>sétimo lugar</strong>.</p>\n\n\n\n<p>Na <strong>próxima rodada</strong>, a sexta do Grupo 7 da <strong>Série D</strong>, o Pérolas Negras novamente atua no Estádio do Trabalhador, diante do São Bernardo-SP, no <strong>domingo (22)</strong>, às 15h. No mesmo dia, mas às <strong>16h</strong>, o <strong>Paraná Clube</strong> encara o <strong>Cianorte</strong>, no <strong>Estádio Albino Turbay</strong>.</p>\n\n\n\n<h2><strong>PÉROLAS NEGRAS 0 X 1 PARANÁ CLUBE</strong></h2>\n\n\n\n<p>O jogo começou amarrado, com as duas equipes em marcha lenta, com dificuldades para criar jogadas. O <strong>Paraná Clube</strong> dava a posse de bola para o <strong>Pérolas Negras</strong>, e tentava sair no contra ataque, porém, o a falta de criatividade atrapalhava o plano.</p>\n\n\n\n<p>A primeira chance do Tricolor foi apenas aos 18 minutos, em cabeçada de Moisés Gaúcho, que não levou perigo ao gol de Rafael Mello. Aos <strong>25</strong>, o <strong>time paranista</strong> teve a <strong>melhor oportunidade</strong> de abrir o placar. Éverton Brito foi derrubado dentro da área. O árbitro José Wellington Bandeira anotou a <strong>penalidade máxima</strong>, <strong>André Krobel</strong> foi para a cobrança, mas <strong>mandou à meia altura</strong>, e o <strong>goleiro </strong>da equipe da casa <strong>fez a defesa</strong>.</p>\n\n\n\n<p>O pênalti perdido pelo <strong>Paraná Clube</strong> recolou o <strong>Pérolas Negras</strong> na partida. A equipe da casa teve sua primeira finalização aos 34, mas o arremate de Andinho parou em Felipe. Aos 43, Andinho teve outra boa oportunidade, mas parou no goleiro paranista, que garantiu o empate parcial.</p>\n\n\n\n<p>A segunda etapa começou com a equipe da casa indo jogando no campo de ataque, tentando encontrar espaços. No entanto, quem <strong>abriu o placar</strong> foi o <strong>Paraná Clube</strong>. Aos 11, Rafael Silva fez o levantamento, <strong>Everton Brito</strong> se antecipou à marcação e <strong>tocou</strong> para o fundo das <strong>redes</strong>.</p>\n\n\n\n<p>O gol deu mais tranquilidade ao Tricolor na partida. O técnico <strong>Omar Feitosa</strong> promoveu as <strong>estreias </strong>de <strong><a href=\"https://ricmais.com.br/futebol/parana-clube-acerta-a-contratacao-do-meia-alisson-taddei-do-sao-joseense/\">Rael e Alisson Taddei</a></strong>, que vieram por empréstimo do São Jossense. Ambos, porém, fizeram uma partida tímida. O <strong>Paraná Clube</strong> diminuiu a intensidade, e viu o <strong>Pérolas Negras</strong> quase chegar ao empate em duas ocasiões.</p>\n\n\n\n<p>Aos 33, Hugo finalizou e obrigou o goleiro Felipe a fazer grande defesa. O arqueiro paranista voltou a salvar aos 37, em novo chute de Hugo. Na sequência, Nandinho aproveitou o rebote, mas Dirceu tirou em cima da linha e garantiu a <strong>importante vitória</strong> do <strong>Tricolor </strong>na competição.</p>\n\n\n\n<p><strong>Ficha Técnica<br>Série D<br>Grupo 7 &#8211; Quinta rodada</strong></p>\n\n\n\n<p><strong><strong>Pérolas Negras:</strong>&nbsp;</strong>Rafael Mello; Ynaiã (Foguete 2ºT/30&#8243;), Carlão, Juan Sosa e Felipe Assis; Franco, Vico (Magno 2ºT/13&#8243;), Andinho (Nandinho 2ºT/24&#8243;) e Gudula; Igor Eto&#8217;o (Hugo 2ºT/24&#8243;) e João Leonardo (Leandrinho 2ºT/24&#8243;)<strong><br><strong>Técnico:&nbsp;</strong></strong>Mauro Fonseca<br><strong>Gols:</strong>&nbsp;<br><strong>Cartões amarelos:</strong>&nbsp;João Leonardo (1ºT/12&#8243;); Carlão (1ºT/45&#8243;); Gudula (2ºT/36&#8243;); Franco (2ºT/43&#8243;)</p>\n\n\n\n<p><strong>Paraná Clube:</strong>&nbsp;Felipe; André Krobel, Franklin, Dirceu e César Morais (Rael 2ºT/15&#8243;); Vinícius Kiss, Moisés Gaúcho e Marcelinho (Milla 2ºT/15&#8243;); Éverton Brito (Ueslei Brito 2ºT/23&#8243;), Rafael Silva (Lucas Buchecha 2ºT/48&#8243;) e Carlos Henrique (Alisson Taddei 2ºT/15&#8243;)<br><strong>Técnico:&nbsp;</strong>Omar Feitosa<br><strong>Gols:</strong>&nbsp;Éverton Brito (2ºT/12&#8243;)<br><strong>Cartões amarelos:</strong>&nbsp;Milla (2ºT/30&#8243;); Alisson Taddei (2ºT/49&#8243;)</p>\n\n\n\n<p><strong>Local</strong>: Estádio do Trabalhador, em Resende (RJ)<br><strong>Data:&nbsp;</strong>15/05/2022<strong><br>Horário:</strong>&nbsp;15h<br><strong>Árbitro:</strong>&nbsp;José Wellington Bandeira (ES)<br><strong>Assistentes:</strong>&nbsp;Thiago Gomes Magalhães (RJ) e Marcus Vinicius Machado Araújo Brandão (RJ)<br><strong>Quarto árbitro:</strong>&nbsp;Bruno Mota Correia (RJ)<br></p>\n",
      "protected": false
    },
    "excerpt": {
      "rendered": "<p>Na tarde deste domingo (15),&nbsp;Pérolas Negras-RJ&nbsp;e&nbsp;Paraná Clube, se enfrentaram, no&nbsp;Estádio do Trabalhador, pela&nbsp;quinta rodada&nbsp;do Grupo 7 da&nbsp;Série D&nbsp;do Campeonato Brasileiro. O Tricolor sofreu mais que o necessário, mas conseguiu vencer a sua segunda partida na competição, e segue dando sequência ao bom momento no campeonato. André Krobel perdeu um pênalti na primeira etapa, mas a [&hellip;]</p>\n",
      "protected": false
    },
    "author": 334,
    "featured_media": 1969271,
    "comment_status": "closed",
    "ping_status": "closed",
    "sticky": false,
    "template": "",
    "format": "standard",
    "meta": [],
    "categories": [
      864
    ],
    "tags": [
      51308,
      51208,
      51628,
      52443
    ],
    "_links": {
      "self": [
        {
          "href": "https://ricmais.com.br/wp-json/wp/v2/posts/1969238"
        }
      ],
      "collection": [
        {
          "href": "https://ricmais.com.br/wp-json/wp/v2/posts"
        }
      ],
      "about": [
        {
          "href": "https://ricmais.com.br/wp-json/wp/v2/types/post"
        }
      ],
      "author": [
        {
          "embeddable": true,
          "href": "https://ricmais.com.br/wp-json/wp/v2/users/334"
        }
      ],
      "replies": [
        {
          "embeddable": true,
          "href": "https://ricmais.com.br/wp-json/wp/v2/comments?post=1969238"
        }
      ],
      "version-history": [
        {
          "count": 0,
          "href": "https://ricmais.com.br/wp-json/wp/v2/posts/1969238/revisions"
        }
      ],
      "wp:featuredmedia": [
        {
          "embeddable": true,
          "href": "https://ricmais.com.br/wp-json/wp/v2/media/1969271"
        }
      ],
      "wp:attachment": [
        {
          "href": "https://ricmais.com.br/wp-json/wp/v2/media?parent=1969238"
        }
      ],
      "wp:term": [
        {
          "taxonomy": "category",
          "embeddable": true,
          "href": "https://ricmais.com.br/wp-json/wp/v2/categories?post=1969238"
        },
        {
          "taxonomy": "post_tag",
          "embeddable": true,
          "href": "https://ricmais.com.br/wp-json/wp/v2/tags?post=1969238"
        }
      ],
      "curies": [
        {
          "name": "wp",
          "href": "https://api.w.org/{rel}",
          "templated": true
        }
      ]
    },
    "_embedded": {
      "author": [
        {
          "id": 334,
          "name": "Guilherme Almeida",
          "url": "",
          "description": "",
          "link": "https://ricmais.com.br/autor/guilherme-almeida/",
          "slug": "guilherme-almeida",
          "avatar_urls": {
            "24": "https://secure.gravatar.com/avatar/3bf05e6a4156492cf3a0cb85fbd77838?s=24&d=mm&r=g",
            "48": "https://secure.gravatar.com/avatar/3bf05e6a4156492cf3a0cb85fbd77838?s=48&d=mm&r=g",
            "96": "https://secure.gravatar.com/avatar/3bf05e6a4156492cf3a0cb85fbd77838?s=96&d=mm&r=g"
          },
          "_links": {
            "self": [
              {
                "href": "https://ricmais.com.br/wp-json/wp/v2/users/334"
              }
            ],
            "collection": [
              {
                "href": "https://ricmais.com.br/wp-json/wp/v2/users"
              }
            ]
          }
        }
      ],
      "wp:featuredmedia": [
        {
          "id": 1969271,
          "date": "2022-05-15T17:02:27",
          "slug": "trab",
          "type": "attachment",
          "link": "https://ricmais.com.br/futebol/parana-clube-vence-perolas-negras-por-1-a-0/attachment/trab/",
          "title": {
            "rendered": "Paraná Clube"
          },
          "author": 334,
          "caption": {
            "rendered": "<p>Estádio do Trabalhador foi o palco da partida (Foto: Anderson Sobrinho/TV Rio Sul)</p>\n"
          },
          "alt_text": "Paraná Clube",
          "media_type": "image",
          "mime_type": "image/jpeg",
          "media_details": {
            "width": 984,
            "height": 738,
            "file": "2022/05/trab.jpg",
            "sizes": {
              "medium": {
                "file": "trab-480x360.jpg",
                "width": 480,
                "height": 360,
                "mime_type": "image/jpeg",
                "source_url": "https://static.ricmais.com.br/uploads/2022/05/trab-480x360.jpg"
              },
              "large": {
                "file": "trab-800x600.jpg",
                "width": 800,
                "height": 600,
                "mime_type": "image/jpeg",
                "source_url": "https://static.ricmais.com.br/uploads/2022/05/trab-800x600.jpg"
              },
              "thumbnail": {
                "file": "trab-150x150.jpg",
                "width": 150,
                "height": 150,
                "mime_type": "image/jpeg",
                "source_url": "https://static.ricmais.com.br/uploads/2022/05/trab-150x150.jpg"
              },
              "medium_large": {
                "file": "trab-768x576.jpg",
                "width": 768,
                "height": 576,
                "mime_type": "image/jpeg",
                "source_url": "https://static.ricmais.com.br/uploads/2022/05/trab-768x576.jpg"
              },
              "thumb_capa_small": {
                "file": "trab-375x250.jpg",
                "width": 375,
                "height": 250,
                "mime_type": "image/jpeg",
                "source_url": "https://static.ricmais.com.br/uploads/2022/05/trab-375x250.jpg"
              },
              "thumb_4_colunas": {
                "file": "trab-255x142.jpg",
                "width": 255,
                "height": 142,
                "mime_type": "image/jpeg",
                "source_url": "https://static.ricmais.com.br/uploads/2022/05/trab-255x142.jpg"
              },
              "thumb_3_colunas": {
                "file": "trab-348x142.jpg",
                "width": 348,
                "height": 142,
                "mime_type": "image/jpeg",
                "source_url": "https://static.ricmais.com.br/uploads/2022/05/trab-348x142.jpg"
              },
              "thumb_programa": {
                "file": "trab-348x164.jpg",
                "width": 348,
                "height": 164,
                "mime_type": "image/jpeg",
                "source_url": "https://static.ricmais.com.br/uploads/2022/05/trab-348x164.jpg"
              },
              "full": {
                "file": "trab.jpg",
                "width": 984,
                "height": 738,
                "mime_type": "image/jpeg",
                "source_url": "https://static.ricmais.com.br/uploads/2022/05/trab.jpg"
              }
            },
            "image_meta": {
              "aperture": "0",
              "credit": "",
              "camera": "",
              "caption": "",
              "created_timestamp": "0",
              "copyright": "",
              "focal_length": "0",
              "iso": "0",
              "shutter_speed": "0",
              "title": "",
              "orientation": "1",
              "keywords": []
            }
          },
          "source_url": "https://static.ricmais.com.br/uploads/2022/05/trab.jpg",
          "_links": {
            "self": [
              {
                "href": "https://ricmais.com.br/wp-json/wp/v2/media/1969271"
              }
            ],
            "collection": [
              {
                "href": "https://ricmais.com.br/wp-json/wp/v2/media"
              }
            ],
            "about": [
              {
                "href": "https://ricmais.com.br/wp-json/wp/v2/types/attachment"
              }
            ],
            "author": [
              {
                "embeddable": true,
                "href": "https://ricmais.com.br/wp-json/wp/v2/users/334"
              }
            ],
            "replies": [
              {
                "embeddable": true,
                "href": "https://ricmais.com.br/wp-json/wp/v2/comments?post=1969271"
              }
            ]
          }
        }
      ],
      "wp:term": [
        [
          {
            "id": 864,
            "link": "https://ricmais.com.br/futebol/",
            "name": "Futebol",
            "slug": "futebol",
            "taxonomy": "category",
            "_links": {
              "self": [
                {
                  "href": "https://ricmais.com.br/wp-json/wp/v2/categories/864"
                }
              ],
              "collection": [
                {
                  "href": "https://ricmais.com.br/wp-json/wp/v2/categories"
                }
              ],
              "about": [
                {
                  "href": "https://ricmais.com.br/wp-json/wp/v2/taxonomies/category"
                }
              ],
              "wp:post_type": [
                {
                  "href": "https://ricmais.com.br/wp-json/wp/v2/posts?categories=864"
                }
              ],
              "curies": [
                {
                  "name": "wp",
                  "href": "https://api.w.org/{rel}",
                  "templated": true
                }
              ]
            }
          }
        ],
        [
          {
            "id": 51308,
            "link": "https://ricmais.com.br/tag/curitiba/",
            "name": "Curitiba",
            "slug": "curitiba",
            "taxonomy": "post_tag",
            "_links": {
              "self": [
                {
                  "href": "https://ricmais.com.br/wp-json/wp/v2/tags/51308"
                }
              ],
              "collection": [
                {
                  "href": "https://ricmais.com.br/wp-json/wp/v2/tags"
                }
              ],
              "about": [
                {
                  "href": "https://ricmais.com.br/wp-json/wp/v2/taxonomies/post_tag"
                }
              ],
              "wp:post_type": [
                {
                  "href": "https://ricmais.com.br/wp-json/wp/v2/posts?tags=51308"
                }
              ],
              "curies": [
                {
                  "name": "wp",
                  "href": "https://api.w.org/{rel}",
                  "templated": true
                }
              ]
            }
          },
          {
            "id": 51208,
            "link": "https://ricmais.com.br/tag/noticia/",
            "name": "Notícia",
            "slug": "noticia",
            "taxonomy": "post_tag",
            "_links": {
              "self": [
                {
                  "href": "https://ricmais.com.br/wp-json/wp/v2/tags/51208"
                }
              ],
              "collection": [
                {
                  "href": "https://ricmais.com.br/wp-json/wp/v2/tags"
                }
              ],
              "about": [
                {
                  "href": "https://ricmais.com.br/wp-json/wp/v2/taxonomies/post_tag"
                }
              ],
              "wp:post_type": [
                {
                  "href": "https://ricmais.com.br/wp-json/wp/v2/posts?tags=51208"
                }
              ],
              "curies": [
                {
                  "name": "wp",
                  "href": "https://api.w.org/{rel}",
                  "templated": true
                }
              ]
            }
          },
          {
            "id": 51628,
            "link": "https://ricmais.com.br/tag/parana/",
            "name": "Paraná",
            "slug": "parana",
            "taxonomy": "post_tag",
            "_links": {
              "self": [
                {
                  "href": "https://ricmais.com.br/wp-json/wp/v2/tags/51628"
                }
              ],
              "collection": [
                {
                  "href": "https://ricmais.com.br/wp-json/wp/v2/tags"
                }
              ],
              "about": [
                {
                  "href": "https://ricmais.com.br/wp-json/wp/v2/taxonomies/post_tag"
                }
              ],
              "wp:post_type": [
                {
                  "href": "https://ricmais.com.br/wp-json/wp/v2/posts?tags=51628"
                }
              ],
              "curies": [
                {
                  "name": "wp",
                  "href": "https://api.w.org/{rel}",
                  "templated": true
                }
              ]
            }
          }
        ]
      ]
    }
  },
  {
    "id": 1969261,
    "date": "2022-05-15T16:49:19",
    "date_gmt": "2022-05-15T19:49:19",
    "guid": {
      "rendered": "https://ricmais.com.br/?p=1969261"
    },
    "modified": "2022-05-15T16:49:24",
    "modified_gmt": "2022-05-15T19:49:24",
    "slug": "onibus-da-agencia-do-trabalhador-estara-em-8-cidades-do-oeste-com-vagas-de-emprego",
    "status": "publish",
    "type": "post",
    "link": "https://ricmais.com.br/empregos/onibus-da-agencia-do-trabalhador-estara-em-8-cidades-do-oeste-com-vagas-de-emprego/",
    "title": {
      "rendered": "Ônibus da Agência do Trabalhador estará em 8 cidades do oeste com vagas de emprego"
    },
    "content": {
      "rendered": "\n<p>O ônibus da Agência do Trabalhador Itinerante percorrerá na segunda quinzena de maio oito municípios da região oeste do Paraná. </p>\n\n\n\n<p>O trajeto começa na segunda-feira (16) em Terra Roxa, seguindo para Mercedes na terça (17), com a oferta de cerca de 200 vagas para os dois municípios.</p>\n\n\n\n<p>Os atendimentos em Terra Roxa ocorrerão Avenida Costa e Silva, em frente à Praça Matriz. Serão disponibilizadas 161 vagas nas áreas de construção civil, indústria e comércio. Os interessados também poderão atualizar o cadastro na rede Sistema Nacional de Emprego (Sine).</p>\n\n\n\n<p>Em Mercedes, o ônibus ficará estacionado na Rua Dr. Osvaldo Cruz 555, em frente à prefeitura. São mais de 46 vagas de emprego nas áreas de serviços, agricultura, comércio e indústria.</p>\n\n\n\n<h2>Cronograma</h2>\n\n\n\n<p>Na sequência, a Agência do Trabalhador Itinerante seguirá para Quatro Pontes, na quinta-feira (19), e Marechal Cândido Rondon, na sexta (20). </p>\n\n\n\n<p>Na semana seguinte estão programadas ações nas cidades de Ouro Verde do Oeste (23), Nova Santa Rosa (24) e Medianeira (26 e 27). O ônibus encerra o itinerário pelo Oeste em Foz do Iguaçu nos dias 30 e 31.</p>\n",
      "protected": false
    },
    "excerpt": {
      "rendered": "<p>O ônibus da Agência do Trabalhador Itinerante percorrerá na segunda quinzena de maio oito municípios da região oeste do Paraná. O trajeto começa na segunda-feira (16) em Terra Roxa, seguindo para Mercedes na terça (17), com a oferta de cerca de 200 vagas para os dois municípios. Os atendimentos em Terra Roxa ocorrerão Avenida Costa [&hellip;]</p>\n",
      "protected": false
    },
    "author": 233,
    "featured_media": 1969268,
    "comment_status": "closed",
    "ping_status": "closed",
    "sticky": false,
    "template": "",
    "format": "standard",
    "meta": [],
    "categories": [
      50926
    ],
    "tags": [
      51034,
      51040,
      51334,
      51418,
      51434,
      51435,
      51208,
      51455,
      51460,
      51505,
      51591
    ],
    "_links": {
      "self": [
        {
          "href": "https://ricmais.com.br/wp-json/wp/v2/posts/1969261"
        }
      ],
      "collection": [
        {
          "href": "https://ricmais.com.br/wp-json/wp/v2/posts"
        }
      ],
      "about": [
        {
          "href": "https://ricmais.com.br/wp-json/wp/v2/types/post"
        }
      ],
      "author": [
        {
          "embeddable": true,
          "href": "https://ricmais.com.br/wp-json/wp/v2/users/233"
        }
      ],
      "replies": [
        {
          "embeddable": true,
          "href": "https://ricmais.com.br/wp-json/wp/v2/comments?post=1969261"
        }
      ],
      "version-history": [
        {
          "count": 0,
          "href": "https://ricmais.com.br/wp-json/wp/v2/posts/1969261/revisions"
        }
      ],
      "wp:featuredmedia": [
        {
          "embeddable": true,
          "href": "https://ricmais.com.br/wp-json/wp/v2/media/1969268"
        }
      ],
      "wp:attachment": [
        {
          "href": "https://ricmais.com.br/wp-json/wp/v2/media?parent=1969261"
        }
      ],
      "wp:term": [
        {
          "taxonomy": "category",
          "embeddable": true,
          "href": "https://ricmais.com.br/wp-json/wp/v2/categories?post=1969261"
        },
        {
          "taxonomy": "post_tag",
          "embeddable": true,
          "href": "https://ricmais.com.br/wp-json/wp/v2/tags?post=1969261"
        }
      ],
      "curies": [
        {
          "name": "wp",
          "href": "https://api.w.org/{rel}",
          "templated": true
        }
      ]
    },
    "_embedded": {
      "author": [
        {
          "id": 233,
          "name": "Redação RIC Mais",
          "url": "",
          "description": "",
          "link": "https://ricmais.com.br/autor/redacao/",
          "slug": "redacao",
          "avatar_urls": {
            "24": "https://secure.gravatar.com/avatar/2dc10d0b11d1c7ef917118536b9ffa58?s=24&d=mm&r=g",
            "48": "https://secure.gravatar.com/avatar/2dc10d0b11d1c7ef917118536b9ffa58?s=48&d=mm&r=g",
            "96": "https://secure.gravatar.com/avatar/2dc10d0b11d1c7ef917118536b9ffa58?s=96&d=mm&r=g"
          },
          "_links": {
            "self": [
              {
                "href": "https://ricmais.com.br/wp-json/wp/v2/users/233"
              }
            ],
            "collection": [
              {
                "href": "https://ricmais.com.br/wp-json/wp/v2/users"
              }
            ]
          }
        }
      ],
      "wp:featuredmedia": [
        {
          "id": 1969268,
          "date": "2022-05-15T16:48:19",
          "slug": "onibus-trabalhadr",
          "type": "attachment",
          "link": "https://ricmais.com.br/empregos/onibus-da-agencia-do-trabalhador-estara-em-8-cidades-do-oeste-com-vagas-de-emprego/attachment/onibus-trabalhadr/",
          "title": {
            "rendered": "onibus-trabalhadr"
          },
          "author": 2190,
          "caption": {
            "rendered": "<p>Ônibus itinerante estará em cidades do oeste (Foto: José Fernando Ogura/AEN)</p>\n"
          },
          "alt_text": "",
          "media_type": "image",
          "mime_type": "image/jpeg",
          "media_details": {
            "width": 2560,
            "height": 1707,
            "file": "2022/05/onibus-trabalhadr-scaled.jpg",
            "sizes": {
              "medium": {
                "file": "onibus-trabalhadr-480x320.jpg",
                "width": 480,
                "height": 320,
                "mime_type": "image/jpeg",
                "source_url": "https://static.ricmais.com.br/uploads/2022/05/onibus-trabalhadr-480x320.jpg"
              },
              "large": {
                "file": "onibus-trabalhadr-900x600.jpg",
                "width": 900,
                "height": 600,
                "mime_type": "image/jpeg",
                "source_url": "https://static.ricmais.com.br/uploads/2022/05/onibus-trabalhadr-900x600.jpg"
              },
              "thumbnail": {
                "file": "onibus-trabalhadr-150x150.jpg",
                "width": 150,
                "height": 150,
                "mime_type": "image/jpeg",
                "source_url": "https://static.ricmais.com.br/uploads/2022/05/onibus-trabalhadr-150x150.jpg"
              },
              "medium_large": {
                "file": "onibus-trabalhadr-768x512.jpg",
                "width": 768,
                "height": 512,
                "mime_type": "image/jpeg",
                "source_url": "https://static.ricmais.com.br/uploads/2022/05/onibus-trabalhadr-768x512.jpg"
              },
              "1536x1536": {
                "file": "onibus-trabalhadr-1536x1024.jpg",
                "width": 1536,
                "height": 1024,
                "mime_type": "image/jpeg",
                "source_url": "https://static.ricmais.com.br/uploads/2022/05/onibus-trabalhadr-1536x1024.jpg"
              },
              "2048x2048": {
                "file": "onibus-trabalhadr-2048x1365.jpg",
                "width": 2048,
                "height": 1365,
                "mime_type": "image/jpeg",
                "source_url": "https://static.ricmais.com.br/uploads/2022/05/onibus-trabalhadr-2048x1365.jpg"
              },
              "thumb_capa_small": {
                "file": "onibus-trabalhadr-375x250.jpg",
                "width": 375,
                "height": 250,
                "mime_type": "image/jpeg",
                "source_url": "https://static.ricmais.com.br/uploads/2022/05/onibus-trabalhadr-375x250.jpg"
              },
              "thumb_4_colunas": {
                "file": "onibus-trabalhadr-255x142.jpg",
                "width": 255,
                "height": 142,
                "mime_type": "image/jpeg",
                "source_url": "https://static.ricmais.com.br/uploads/2022/05/onibus-trabalhadr-255x142.jpg"
              },
              "thumb_3_colunas": {
                "file": "onibus-trabalhadr-348x142.jpg",
                "width": 348,
                "height": 142,
                "mime_type": "image/jpeg",
                "source_url": "https://static.ricmais.com.br/uploads/2022/05/onibus-trabalhadr-348x142.jpg"
              },
              "thumb_programa": {
                "file": "onibus-trabalhadr-348x164.jpg",
                "width": 348,
                "height": 164,
                "mime_type": "image/jpeg",
                "source_url": "https://static.ricmais.com.br/uploads/2022/05/onibus-trabalhadr-348x164.jpg"
              },
              "full": {
                "file": "onibus-trabalhadr-scaled.jpg",
                "width": 2560,
                "height": 1707,
                "mime_type": "image/jpeg",
                "source_url": "https://static.ricmais.com.br/uploads/2022/05/onibus-trabalhadr-scaled.jpg"
              }
            },
            "image_meta": {
              "aperture": "5",
              "credit": "@JFOGURA",
              "camera": "Canon EOS 90D",
              "caption": "",
              "created_timestamp": "1643738136",
              "copyright": "@JOSE FERNANDO OGURA",
              "focal_length": "13",
              "iso": "2000",
              "shutter_speed": "0.00015625",
              "title": "",
              "orientation": "1",
              "keywords": []
            },
            "original_image": "onibus-trabalhadr.jpg"
          },
          "source_url": "https://static.ricmais.com.br/uploads/2022/05/onibus-trabalhadr-scaled.jpg",
          "_links": {
            "self": [
              {
                "href": "https://ricmais.com.br/wp-json/wp/v2/media/1969268"
              }
            ],
            "collection": [
              {
                "href": "https://ricmais.com.br/wp-json/wp/v2/media"
              }
            ],
            "about": [
              {
                "href": "https://ricmais.com.br/wp-json/wp/v2/types/attachment"
              }
            ],
            "author": [
              {
                "embeddable": true,
                "href": "https://ricmais.com.br/wp-json/wp/v2/users/2190"
              }
            ],
            "replies": [
              {
                "embeddable": true,
                "href": "https://ricmais.com.br/wp-json/wp/v2/comments?post=1969268"
              }
            ]
          }
        }
      ],
      "wp:term": [
        [
          {
            "id": 50926,
            "link": "https://ricmais.com.br/empregos/",
            "name": "Empregos",
            "slug": "empregos",
            "taxonomy": "category",
            "_links": {
              "self": [
                {
                  "href": "https://ricmais.com.br/wp-json/wp/v2/categories/50926"
                }
              ],
              "collection": [
                {
                  "href": "https://ricmais.com.br/wp-json/wp/v2/categories"
                }
              ],
              "about": [
                {
                  "href": "https://ricmais.com.br/wp-json/wp/v2/taxonomies/category"
                }
              ],
              "wp:post_type": [
                {
                  "href": "https://ricmais.com.br/wp-json/wp/v2/posts?categories=50926"
                }
              ],
              "curies": [
                {
                  "name": "wp",
                  "href": "https://api.w.org/{rel}",
                  "templated": true
                }
              ]
            }
          }
        ],
        [
          {
            "id": 51034,
            "link": "https://ricmais.com.br/tag/cotidiano/",
            "name": "Cotidiano",
            "slug": "cotidiano",
            "taxonomy": "post_tag",
            "_links": {
              "self": [
                {
                  "href": "https://ricmais.com.br/wp-json/wp/v2/tags/51034"
                }
              ],
              "collection": [
                {
                  "href": "https://ricmais.com.br/wp-json/wp/v2/tags"
                }
              ],
              "about": [
                {
                  "href": "https://ricmais.com.br/wp-json/wp/v2/taxonomies/post_tag"
                }
              ],
              "wp:post_type": [
                {
                  "href": "https://ricmais.com.br/wp-json/wp/v2/posts?tags=51034"
                }
              ],
              "curies": [
                {
                  "name": "wp",
                  "href": "https://api.w.org/{rel}",
                  "templated": true
                }
              ]
            }
          },
          {
            "id": 51040,
            "link": "https://ricmais.com.br/tag/economia/",
            "name": "Economia",
            "slug": "economia",
            "taxonomy": "post_tag",
            "_links": {
              "self": [
                {
                  "href": "https://ricmais.com.br/wp-json/wp/v2/tags/51040"
                }
              ],
              "collection": [
                {
                  "href": "https://ricmais.com.br/wp-json/wp/v2/tags"
                }
              ],
              "about": [
                {
                  "href": "https://ricmais.com.br/wp-json/wp/v2/taxonomies/post_tag"
                }
              ],
              "wp:post_type": [
                {
                  "href": "https://ricmais.com.br/wp-json/wp/v2/posts?tags=51040"
                }
              ],
              "curies": [
                {
                  "name": "wp",
                  "href": "https://api.w.org/{rel}",
                  "templated": true
                }
              ]
            }
          },
          {
            "id": 51334,
            "link": "https://ricmais.com.br/tag/foz-do-iguacu/",
            "name": "Foz do Iguaçu",
            "slug": "foz-do-iguacu",
            "taxonomy": "post_tag",
            "_links": {
              "self": [
                {
                  "href": "https://ricmais.com.br/wp-json/wp/v2/tags/51334"
                }
              ],
              "collection": [
                {
                  "href": "https://ricmais.com.br/wp-json/wp/v2/tags"
                }
              ],
              "about": [
                {
                  "href": "https://ricmais.com.br/wp-json/wp/v2/taxonomies/post_tag"
                }
              ],
              "wp:post_type": [
                {
                  "href": "https://ricmais.com.br/wp-json/wp/v2/posts?tags=51334"
                }
              ],
              "curies": [
                {
                  "name": "wp",
                  "href": "https://api.w.org/{rel}",
                  "templated": true
                }
              ]
            }
          },
          {
            "id": 51418,
            "link": "https://ricmais.com.br/tag/marechal-candido-rondon/",
            "name": "Marechal Cândido Rondon",
            "slug": "marechal-candido-rondon",
            "taxonomy": "post_tag",
            "_links": {
              "self": [
                {
                  "href": "https://ricmais.com.br/wp-json/wp/v2/tags/51418"
                }
              ],
              "collection": [
                {
                  "href": "https://ricmais.com.br/wp-json/wp/v2/tags"
                }
              ],
              "about": [
                {
                  "href": "https://ricmais.com.br/wp-json/wp/v2/taxonomies/post_tag"
                }
              ],
              "wp:post_type": [
                {
                  "href": "https://ricmais.com.br/wp-json/wp/v2/posts?tags=51418"
                }
              ],
              "curies": [
                {
                  "name": "wp",
                  "href": "https://api.w.org/{rel}",
                  "templated": true
                }
              ]
            }
          },
          {
            "id": 51434,
            "link": "https://ricmais.com.br/tag/medianeira/",
            "name": "Medianeira",
            "slug": "medianeira",
            "taxonomy": "post_tag",
            "_links": {
              "self": [
                {
                  "href": "https://ricmais.com.br/wp-json/wp/v2/tags/51434"
                }
              ],
              "collection": [
                {
                  "href": "https://ricmais.com.br/wp-json/wp/v2/tags"
                }
              ],
              "about": [
                {
                  "href": "https://ricmais.com.br/wp-json/wp/v2/taxonomies/post_tag"
                }
              ],
              "wp:post_type": [
                {
                  "href": "https://ricmais.com.br/wp-json/wp/v2/posts?tags=51434"
                }
              ],
              "curies": [
                {
                  "name": "wp",
                  "href": "https://api.w.org/{rel}",
                  "templated": true
                }
              ]
            }
          },
          {
            "id": 51435,
            "link": "https://ricmais.com.br/tag/mercedes/",
            "name": "Mercedes",
            "slug": "mercedes",
            "taxonomy": "post_tag",
            "_links": {
              "self": [
                {
                  "href": "https://ricmais.com.br/wp-json/wp/v2/tags/51435"
                }
              ],
              "collection": [
                {
                  "href": "https://ricmais.com.br/wp-json/wp/v2/tags"
                }
              ],
              "about": [
                {
                  "href": "https://ricmais.com.br/wp-json/wp/v2/taxonomies/post_tag"
                }
              ],
              "wp:post_type": [
                {
                  "href": "https://ricmais.com.br/wp-json/wp/v2/posts?tags=51435"
                }
              ],
              "curies": [
                {
                  "name": "wp",
                  "href": "https://api.w.org/{rel}",
                  "templated": true
                }
              ]
            }
          },
          {
            "id": 51208,
            "link": "https://ricmais.com.br/tag/noticia/",
            "name": "Notícia",
            "slug": "noticia",
            "taxonomy": "post_tag",
            "_links": {
              "self": [
                {
                  "href": "https://ricmais.com.br/wp-json/wp/v2/tags/51208"
                }
              ],
              "collection": [
                {
                  "href": "https://ricmais.com.br/wp-json/wp/v2/tags"
                }
              ],
              "about": [
                {
                  "href": "https://ricmais.com.br/wp-json/wp/v2/taxonomies/post_tag"
                }
              ],
              "wp:post_type": [
                {
                  "href": "https://ricmais.com.br/wp-json/wp/v2/posts?tags=51208"
                }
              ],
              "curies": [
                {
                  "name": "wp",
                  "href": "https://api.w.org/{rel}",
                  "templated": true
                }
              ]
            }
          },
          {
            "id": 51455,
            "link": "https://ricmais.com.br/tag/nova-santa-rosa/",
            "name": "Nova Santa Rosa",
            "slug": "nova-santa-rosa",
            "taxonomy": "post_tag",
            "_links": {
              "self": [
                {
                  "href": "https://ricmais.com.br/wp-json/wp/v2/tags/51455"
                }
              ],
              "collection": [
                {
                  "href": "https://ricmais.com.br/wp-json/wp/v2/tags"
                }
              ],
              "about": [
                {
                  "href": "https://ricmais.com.br/wp-json/wp/v2/taxonomies/post_tag"
                }
              ],
              "wp:post_type": [
                {
                  "href": "https://ricmais.com.br/wp-json/wp/v2/posts?tags=51455"
                }
              ],
              "curies": [
                {
                  "name": "wp",
                  "href": "https://api.w.org/{rel}",
                  "templated": true
                }
              ]
            }
          },
          {
            "id": 51460,
            "link": "https://ricmais.com.br/tag/ouro-verde-do-oeste/",
            "name": "Ouro Verde do Oeste",
            "slug": "ouro-verde-do-oeste",
            "taxonomy": "post_tag",
            "_links": {
              "self": [
                {
                  "href": "https://ricmais.com.br/wp-json/wp/v2/tags/51460"
                }
              ],
              "collection": [
                {
                  "href": "https://ricmais.com.br/wp-json/wp/v2/tags"
                }
              ],
              "about": [
                {
                  "href": "https://ricmais.com.br/wp-json/wp/v2/taxonomies/post_tag"
                }
              ],
              "wp:post_type": [
                {
                  "href": "https://ricmais.com.br/wp-json/wp/v2/posts?tags=51460"
                }
              ],
              "curies": [
                {
                  "name": "wp",
                  "href": "https://api.w.org/{rel}",
                  "templated": true
                }
              ]
            }
          },
          {
            "id": 51505,
            "link": "https://ricmais.com.br/tag/quatro-pontes/",
            "name": "Quatro Pontes",
            "slug": "quatro-pontes",
            "taxonomy": "post_tag",
            "_links": {
              "self": [
                {
                  "href": "https://ricmais.com.br/wp-json/wp/v2/tags/51505"
                }
              ],
              "collection": [
                {
                  "href": "https://ricmais.com.br/wp-json/wp/v2/tags"
                }
              ],
              "about": [
                {
                  "href": "https://ricmais.com.br/wp-json/wp/v2/taxonomies/post_tag"
                }
              ],
              "wp:post_type": [
                {
                  "href": "https://ricmais.com.br/wp-json/wp/v2/posts?tags=51505"
                }
              ],
              "curies": [
                {
                  "name": "wp",
                  "href": "https://api.w.org/{rel}",
                  "templated": true
                }
              ]
            }
          }
        ]
      ]
    }
  }
]